odoo/addons/auth_ldaps/README.rst
odoo/addons/auth_ldaps/__init__.py
odoo/addons/auth_ldaps/__manifest__.py
odoo/addons/auth_ldaps/i18n/auth_ldaps.pot
odoo/addons/auth_ldaps/i18n/it.po
odoo/addons/auth_ldaps/models/__init__.py
odoo/addons/auth_ldaps/models/res_company_ldap.py
odoo/addons/auth_ldaps/static/description/icon.png
odoo/addons/auth_ldaps/views/res_company_ldap_views.xml
odoo12_addon_auth_ldaps-12.0.1.0.1.dist-info/METADATA
odoo12_addon_auth_ldaps-12.0.1.0.1.dist-info/WHEEL
odoo12_addon_auth_ldaps-12.0.1.0.1.dist-info/top_level.txt
odoo12_addon_auth_ldaps-12.0.1.0.1.dist-info/RECORD
